{"cameraMode":{"drawMode":0,"name":"Shaded","section":"Shading Mode"},"sceneLighting":false,"audioPlay":false,"sceneViewState":{"m_AlwaysRefresh":false,"showFog":true,"showSkybox":false,"showFlares":true,"showImageEffects":true,"showParticleSystems":true,"showVisualEffectGraphs":true,"m_FxEnabled":true},"in2DMode":false,"pivot":{"x":-31.275985717773439,"y":5.1283721923828129,"z":0.9095993041992188},"rotation":{"x":-0.1443331092596054,"y":0.45614081621170046,"z":-0.0752527117729187,"w":-0.8748995661735535},"size":99.44560241699219,"orthographic":false}