{"cameraMode":{"drawMode":0,"name":"Shaded","section":"Shading Mode"},"sceneLighting":true,"audioPlay":false,"sceneViewState":{"m_AlwaysRefresh":false,"showFog":true,"showSkybox":true,"showFlares":true,"showImageEffects":true,"showParticleSystems":true,"showVisualEffectGraphs":true,"m_FxEnabled":true},"in2DMode":false,"pivot":{"x":5.222795486450195,"y":-5.461630821228027,"z":22.90817642211914},"rotation":{"x":0.14455336332321168,"y":0.15955278277397157,"z":-0.023624679073691369,"w":0.9762628078460693},"size":19.772903442382814,"orthographic":false}